{"cameraMode":{"drawMode":0,"name":"Shaded","section":"Shading Mode"},"sceneLighting":true,"audioPlay":false,"sceneViewState":{"m_AlwaysRefresh":false,"showFog":true,"showSkybox":true,"showFlares":true,"showImageEffects":true,"showParticleSystems":true,"showVisualEffectGraphs":true,"m_FxEnabled":true},"in2DMode":false,"pivot":{"x":1.3420944213867188,"y":4.9204864501953129,"z":-3.421149253845215},"rotation":{"x":-0.0337647944688797,"y":0.9456226825714111,"z":-0.10425786674022675,"w":-0.30624809861183169},"size":10.898137092590332,"orthographic":false}